pytest_collect_markers/__init__.py
pytest_collect_markers-0.2.0.dist-info/WHEEL
pytest_collect_markers-0.2.0.dist-info/entry_points.txt
pytest_collect_markers-0.2.0.dist-info/METADATA
pytest_collect_markers-0.2.0.dist-info/RECORD
