Metadata-Version: 2.3
Name: pytest-collect-markers
Version: 0.2.0
Summary: A pytest plugin to collect and output test markers to JSON
Requires-Dist: pytest>=7.0.0
Requires-Python: >=3.10
